thonny_crosshair-0.0.1.data/data/LICENSE
thonny_crosshair-0.0.1.data/data/README.rst
thonny_crosshair-0.0.1.data/data/requirements.txt
thonnycontrib/thonny_crosshair/__init__.py
thonnycontrib/thonny_crosshair/py.typed
thonny_crosshair-0.0.1.dist-info/LICENSE
thonny_crosshair-0.0.1.dist-info/METADATA
thonny_crosshair-0.0.1.dist-info/WHEEL
thonny_crosshair-0.0.1.dist-info/top_level.txt
thonny_crosshair-0.0.1.dist-info/RECORD
