Metadata-Version: 2.1
Name: thonny-crosshair
Version: 0.0.1
Summary: Automatically verify Python code using CrossHair in Thonny.
Home-page: https://github.com/mristin/thonny-crosshair
Author: Marko Ristin
Author-email: marko@ristin.ch
License: License :: OSI Approved :: MIT License
Keywords: design-by-contract contracts automatic verification
Platform: UNKNOWN
Classifier: Development Status :: 5 - Production/Stable
Classifier: Environment :: MacOS X
Classifier: Environment :: Win32 (MS Windows)
Classifier: Environment :: X11 Applications
Classifier: Intended Audience :: Developers
Classifier: Intended Audience :: Education
Classifier: Intended Audience :: End Users/Desktop
Classifier: License :: Freeware
Classifier: License :: OSI Approved :: MIT License
Classifier: Natural Language :: English
Classifier: Operating System :: MacOS
Classifier: Operating System :: Microsoft :: Windows
Classifier: Operating System :: POSIX
Classifier: Operating System :: POSIX :: Linux
Classifier: Programming Language :: Python
Classifier: Programming Language :: Python :: 3
Classifier: Programming Language :: Python :: 3 :: Only
Classifier: Programming Language :: Python :: 3.7
Classifier: Programming Language :: Python :: 3.8
Classifier: Topic :: Education
Classifier: Topic :: Software Development
Classifier: Topic :: Software Development :: Debuggers
Requires-Python: >=3.7
Requires-Dist: thonny (<4,>=3.0.0)
Requires-Dist: crosshair-tool (<2,>=0.0.13)
Requires-Dist: icontract
Provides-Extra: dev
Requires-Dist: black (==20.8b1) ; extra == 'dev'
Requires-Dist: mypy (==0.812) ; extra == 'dev'
Requires-Dist: pylint (==2.3.1) ; extra == 'dev'
Requires-Dist: pydocstyle (<3,>=2.1.1) ; extra == 'dev'
Requires-Dist: coverage (<5,>=4.5.1) ; extra == 'dev'
Requires-Dist: docutils (<1,>=0.14) ; extra == 'dev'
